<mxGraphModel dx="457" dy="624" grid="1" gridSize="10" guides="1" tooltips="1" connect="1" arrows="1" fold="1" page="1" pageScale="1" pageWidth="827" pageHeight="1169">
    <root>
        <mxCell id="0"/>
        <mxCell id="1" style="locked=0" parent="0"/>
        <mxCell id="15" style="edgeStyle=orthogonalEdgeStyle;rounded=0;orthogonalLoop=1;jettySize=auto;html=1;exitX=1;exitY=0.5;exitDx=0;exitDy=0;exitPerimeter=0;" edge="1" parent="1" source="2" target="3">
            <mxGeometry relative="1" as="geometry"/>
        </mxCell>
        <mxCell id="2" value="" style="shape=flow.startnode;whiteSpace=wrap;html=1;fillColor=#ffffff;strokeColor=#000000;strokeWidth=2" vertex="1" parent="1">
            <mxGeometry x="120" y="100" width="50" height="50" as="geometry"/>
        </mxCell>
        <mxCell id="16" style="edgeStyle=orthogonalEdgeStyle;rounded=0;orthogonalLoop=1;jettySize=auto;html=1;exitX=1;exitY=0.5;exitDx=0;exitDy=0;exitPerimeter=0;entryX=0.034;entryY=0.66;entryDx=0;entryDy=0;entryPerimeter=0;" edge="1" parent="1" source="3" target="4">
            <mxGeometry relative="1" as="geometry"/>
        </mxCell>
        <object label="" sync="{&quot;request&quot;:[&quot;c&quot;], &quot;wait&quot;:[],&quot;block&quot;:[]}" Request="&quot;c&quot;" Wait="" Block="" id="3">
            <mxCell style="shape=flow.bsync;whiteSpace=wrap;html=1;fillColor=#ffffff;strokeColor=#000000;strokeWidth=2" vertex="1" parent="1">
                <mxGeometry x="260" y="112.5" width="100" height="25" as="geometry"/>
            </mxCell>
        </object>
        <mxCell id="20" style="edgeStyle=orthogonalEdgeStyle;rounded=0;orthogonalLoop=1;jettySize=auto;html=1;exitX=1;exitY=0.5;exitDx=0;exitDy=0;exitPerimeter=0;entryX=0.041;entryY=0.711;entryDx=0;entryDy=0;entryPerimeter=0;" edge="1" parent="1" source="4" target="17">
            <mxGeometry relative="1" as="geometry"/>
        </mxCell>
        <object label="" sync="{&quot;request&quot;:[&quot;c&quot;], &quot;wait&quot;:[],&quot;block&quot;:[]}" Request="&quot;c&quot;" Wait="" Block="" id="4">
            <mxCell style="shape=flow.bsync;whiteSpace=wrap;html=1;fillColor=#ffffff;strokeColor=#000000;strokeWidth=2" vertex="1" parent="1">
                <mxGeometry x="440" y="112.5" width="100" height="25" as="geometry"/>
            </mxCell>
        </object>
        <mxCell id="13" style="edgeStyle=orthogonalEdgeStyle;rounded=0;orthogonalLoop=1;jettySize=auto;html=1;exitX=1;exitY=0.5;exitDx=0;exitDy=0;exitPerimeter=0;" edge="1" parent="1" source="5" target="6">
            <mxGeometry relative="1" as="geometry"/>
        </mxCell>
        <mxCell id="5" value="" style="shape=flow.startnode;whiteSpace=wrap;html=1;fillColor=#ffffff;strokeColor=#000000;strokeWidth=2" vertex="1" parent="1">
            <mxGeometry x="120" y="290" width="50" height="50" as="geometry"/>
        </mxCell>
        <mxCell id="14" style="edgeStyle=orthogonalEdgeStyle;rounded=0;orthogonalLoop=1;jettySize=auto;html=1;exitX=1;exitY=0.5;exitDx=0;exitDy=0;exitPerimeter=0;" edge="1" parent="1" source="6" target="7">
            <mxGeometry relative="1" as="geometry"/>
        </mxCell>
        <object label="" sync="{&quot;request&quot;:[&quot;h&quot;], &quot;wait&quot;:[],&quot;block&quot;:[]}" Request="&quot;h&quot;" Wait="" Block="" id="6">
            <mxCell style="shape=flow.bsync;whiteSpace=wrap;html=1;fillColor=#ffffff;strokeColor=#000000;strokeWidth=2" vertex="1" parent="1">
                <mxGeometry x="280" y="303" width="100" height="25" as="geometry"/>
            </mxCell>
        </object>
        <mxCell id="19" style="edgeStyle=orthogonalEdgeStyle;rounded=0;orthogonalLoop=1;jettySize=auto;html=1;exitX=1;exitY=0.5;exitDx=0;exitDy=0;exitPerimeter=0;entryX=0.012;entryY=0.436;entryDx=0;entryDy=0;entryPerimeter=0;" edge="1" parent="1" source="7" target="18">
            <mxGeometry relative="1" as="geometry"/>
        </mxCell>
        <object label="" sync="{&quot;request&quot;:[&quot;h&quot;], &quot;wait&quot;:[],&quot;block&quot;:[]}" Request="&quot;h&quot;" Wait="" Block="" id="7">
            <mxCell style="shape=flow.bsync;whiteSpace=wrap;html=1;fillColor=#ffffff;strokeColor=#000000;strokeWidth=2" vertex="1" parent="1">
                <mxGeometry x="440" y="303" width="100" height="25" as="geometry"/>
            </mxCell>
        </object>
        <mxCell id="11" style="edgeStyle=orthogonalEdgeStyle;rounded=0;orthogonalLoop=1;jettySize=auto;html=1;exitX=1;exitY=0.5;exitDx=0;exitDy=0;exitPerimeter=0;entryX=0.046;entryY=0.338;entryDx=0;entryDy=0;entryPerimeter=0;" edge="1" parent="1" source="8" target="9">
            <mxGeometry relative="1" as="geometry"/>
        </mxCell>
        <mxCell id="8" value="" style="shape=flow.startnode;whiteSpace=wrap;html=1;fillColor=#ffffff;strokeColor=#000000;strokeWidth=2" vertex="1" parent="1">
            <mxGeometry x="110" y="480" width="50" height="50" as="geometry"/>
        </mxCell>
        <mxCell id="12" style="edgeStyle=orthogonalEdgeStyle;rounded=0;orthogonalLoop=1;jettySize=auto;html=1;exitX=1;exitY=0.5;exitDx=0;exitDy=0;exitPerimeter=0;entryX=-0.03;entryY=0.642;entryDx=0;entryDy=0;entryPerimeter=0;" edge="1" parent="1" source="9" target="10">
            <mxGeometry relative="1" as="geometry"/>
        </mxCell>
        <object label="" sync="{&quot;request&quot;:[], &quot;wait&quot;:[&quot;h&quot;],&quot;block&quot;:[&quot;c&quot;]}" Request="" Wait="&quot;h&quot;" Block="&quot;c&quot;" id="9">
            <mxCell style="shape=flow.bsync;whiteSpace=wrap;html=1;fillColor=#ffffff;strokeColor=#000000;strokeWidth=2" vertex="1" parent="1">
                <mxGeometry x="310" y="493" width="100" height="25" as="geometry"/>
            </mxCell>
        </object>
        <mxCell id="22" style="edgeStyle=orthogonalEdgeStyle;rounded=0;orthogonalLoop=1;jettySize=auto;html=1;exitX=1;exitY=0.5;exitDx=0;exitDy=0;exitPerimeter=0;entryX=0.001;entryY=0.658;entryDx=0;entryDy=0;entryPerimeter=0;" edge="1" parent="1" source="10" target="9">
            <mxGeometry relative="1" as="geometry"/>
        </mxCell>
        <object label="" sync="{&quot;request&quot;:[], &quot;wait&quot;:[&quot;c&quot;],&quot;block&quot;:[&quot;h&quot;]}" Request="" Wait="&quot;c&quot;" Block="&quot;h&quot;" id="10">
            <mxCell style="shape=flow.bsync;whiteSpace=wrap;html=1;fillColor=#ffffff;strokeColor=#000000;strokeWidth=2" vertex="1" parent="1">
                <mxGeometry x="490" y="492.5" width="100" height="25" as="geometry"/>
            </mxCell>
        </object>
        <object label="" sync="{&quot;request&quot;:[&quot;c&quot;], &quot;wait&quot;:[],&quot;block&quot;:[]}" Request="&quot;c&quot;" Wait="" Block="" id="17">
            <mxCell style="shape=flow.bsync;whiteSpace=wrap;html=1;fillColor=#ffffff;strokeColor=#000000;strokeWidth=2" vertex="1" parent="1">
                <mxGeometry x="650" y="113" width="100" height="25" as="geometry"/>
            </mxCell>
        </object>
        <object label="" sync="{&quot;request&quot;:[&quot;h&quot;], &quot;wait&quot;:[],&quot;block&quot;:[]}" Request="&quot;h&quot;" Wait="" Block="" id="18">
            <mxCell style="shape=flow.bsync;whiteSpace=wrap;html=1;fillColor=#ffffff;strokeColor=#000000;strokeWidth=2" vertex="1" parent="1">
                <mxGeometry x="660" y="303" width="100" height="25" as="geometry"/>
            </mxCell>
        </object>
    </root>
</mxGraphModel>